NCBITK/__init__.py
NCBITK/__main__.py
NCBITK/config.py
NCBITK/curate.py
NCBITK/get_resources.py
NCBITK/sync.py
NCBITK-1.0a17.dist-info/DESCRIPTION.rst
NCBITK-1.0a17.dist-info/METADATA
NCBITK-1.0a17.dist-info/RECORD
NCBITK-1.0a17.dist-info/WHEEL
NCBITK-1.0a17.dist-info/entry_points.txt
NCBITK-1.0a17.dist-info/metadata.json
NCBITK-1.0a17.dist-info/top_level.txt
