Metadata-Version: 2.0
Name: NCBITK
Version: 1.0a17
Summary: A tool kit for accessing NCBI's GenBank
Home-page: https://github.com/andrewsanchez/NCBITK
Author: Andrew Sanchez
Author-email: inbox.asanchez@gmail.com
License: MIT
Keywords: NCBI bioinformatics
Platform: UNKNOWN
Classifier: Topic :: Scientific/Engineering :: Bio-Informatics
Classifier: Programming Language :: Python :: 3.6
Classifier: Operating System :: POSIX :: Linux
Classifier: License :: OSI Approved :: MIT License
Classifier: Intended Audience :: Science/Research
Classifier: Environment :: Console
Classifier: Development Status :: 3 - Alpha
Requires-Dist: biopython (>=1.68)
Requires-Dist: click
Requires-Dist: numpy (>=1.12.0)
Requires-Dist: pandas (>=0.19.2)
Requires-Dist: python-dateutil (>=2.6.0)
Requires-Dist: pytz (>=2016.10)
Requires-Dist: six (>=1.10.0)
